Pyflix/__init__.py
Pyflix/torrent/__init__.py
Pyflix/torrent/moov.py
Pyflix/torrent/strategy.py
Pyflix/utils/__init__.py
Pyflix/utils/constants.py
Pyflix/utils/decorators.py
Pyflix/utils/helpers.py
Pyflix/utils/logger.py
Pyflix/utils/output.py
Pyflix/utils/settings.py
Pyflix/utils/streamer.py
torrent_dl-0.0.1.dist-info/DESCRIPTION.rst
torrent_dl-0.0.1.dist-info/METADATA
torrent_dl-0.0.1.dist-info/RECORD
torrent_dl-0.0.1.dist-info/WHEEL
torrent_dl-0.0.1.dist-info/entry_points.txt
torrent_dl-0.0.1.dist-info/metadata.json
torrent_dl-0.0.1.dist-info/top_level.txt
