Metadata-Version: 2.0
Name: torrent-dl
Version: 0.0.1
Summary: Python library to watch and download torrents at the same time
Home-page: https://github.com/animeshkundu/torrent-dl
Author: Animesh Kundu
Author-email: anik.edu@gmail.com
License: LICENSE.txt
Platform: UNKNOWN
Requires-Dist: Ojota (==3.1.2)
Requires-Dist: PyYAML (==3.12)
Requires-Dist: altasetting (==0.1.1)
Requires-Dist: babelfish (==0.5.5)
Requires-Dist: blessings (==1.6)
Requires-Dist: colorama (==0.3.7)
Requires-Dist: docutils (==0.12)
Requires-Dist: guessit (==2.1.0)
Requires-Dist: lockfile (==0.12.2)
Requires-Dist: netifaces (==0.10.5)
Requires-Dist: pyaml (==16.9.0)
Requires-Dist: python-daemon (==2.1.1)
Requires-Dist: python-dateutil (==2.5.3)
Requires-Dist: qtfaststart (==1.8)
Requires-Dist: rebulk (==0.7.6)
Requires-Dist: six (==1.10.0)
